<?xml version="1.0" encoding="utf-8"?>
<PlatformInfo>
	<Platform Name="Windows" BasePlatform="Windows" Generator="2023.1.4.8496"/>
	<RootPaths>
		<ProjectRoot>../../GodotIntegration</ProjectRoot>
		<SourceFilesRoot>../../GodotIntegration/.cache/Windows</SourceFilesRoot>
		<SoundBanksRoot>.</SoundBanksRoot>
		<ExternalSourcesInputFile></ExternalSourcesInputFile>
		<ExternalSourcesOutputRoot>../../GodotIntegration/GeneratedSoundBanks/Windows</ExternalSourcesOutputRoot>
	</RootPaths>
	<DefaultAlign>16</DefaultAlign>
	<Settings>
		<AutoSoundBankDefinition>false</AutoSoundBankDefinition>
		<CopyLooseStreamedMediaFiles>true</CopyLooseStreamedMediaFiles>
		<SubFoldersForGeneratedFiles>false</SubFoldersForGeneratedFiles>
		<RemoveUnusedGeneratedFiles>true</RemoveUnusedGeneratedFiles>
		<SourceControlGeneratedFiles>false</SourceControlGeneratedFiles>
		<GenerateHeaderFile>false</GenerateHeaderFile>
		<GenerateContentTxtFile>true</GenerateContentTxtFile>
		<GenerateMetadataXML>true</GenerateMetadataXML>
		<GenerateMetadataJSON>false</GenerateMetadataJSON>
		<GenerateAllBanksMetadata>true</GenerateAllBanksMetadata>
		<GeneratePerBankMetadata>false</GeneratePerBankMetadata>
		<UseSoundBankNames>true</UseSoundBankNames>
		<AllowExceedingMaxSize>false</AllowExceedingMaxSize>
		<MaxAttenuationInfo>false</MaxAttenuationInfo>
		<EstimatedDurationInfo>false</EstimatedDurationInfo>
		<PrintObjectGuid>false</PrintObjectGuid>
		<PrintObjectPath>false</PrintObjectPath>
	</Settings>
	<FileHash>{DA8D7A16-0879-B542-5299-54A73A360A50}</FileHash>
</PlatformInfo>
